sashimi/__init__.py
sashimi/config.py
sashimi/entropies.py
sashimi/ioio.py
sashimi/misc.py
sashimi/naming.py
sashimi/scorology.py
sashimi/vector_models.py
sashimi/w2v_score.py
sashimi/blocks/__init__.py
sashimi/blocks/annotations.py
sashimi/blocks/area_rank_chart.py
sashimi/blocks/better_network_map.py
sashimi/blocks/block_ext_map.py
sashimi/blocks/hierarchical_block_map.py
sashimi/blocks/hierarchical_block_map_help.html
sashimi/blocks/link_maps.py
sashimi/blocks/network_map.py
sashimi/blocks/util.py
sashimi/blocks/zmethods.py
sashimi/blocks/tables/__init__.py
sashimi/blocks/tables/tables.css
sashimi/blocks/tables/tables_html.py
sashimi/blocks/tables/tables_plots.py
sashimi/corpus/__init__.py
sashimi/corpus/nlp.py
sashimi/corpus/parsers.py
sashimi/corpus/wos.py
sashimi/graph_models/__init__.py
sashimi/graph_models/blockstate_to_dataframes.py
sashimi/graph_models/domain_chained_model.py
sashimi/graph_models/domain_topic_model.py
sashimi/graph_models/util.py
sashimi/util/asco_clean.py
sashimi/util/pubmed_clean.py
sashimi/util/pubmed_get.sh
sashimi/util/scan_bugtrap.py
sashimi/util/wos_lam/__init__.py
sashimi/util/wos_lam/wos_api_request.tpl
sashimi_domains-0.9.7.dist-info/METADATA
sashimi_domains-0.9.7.dist-info/WHEEL
sashimi_domains-0.9.7.dist-info/licenses/LICENSE
sashimi_domains-0.9.7.dist-info/RECORD
