Metadata-Version: 2.3
Name: sashimi-domains
Version: 0.9.7
Summary: A Python module for mixed-methods qualitative studies of large textual or symbolic corpora, providing applications of statistical models accompanied by tailored interactive visualizations. It affords the detection of both textual and metadata structures by employing stochastic block modeling (SBM) from `graph-tool` or (currently deprecated) word embedding from `gensim`.
Project-URL: Documentation, https://gitlab.com/solstag/sashimi/
Project-URL: Issues, https://gitlab.com/solstag/sashimi/-/issues
Project-URL: Source, https://gitlab.com/solstag/sashimi/
Author-email: Ale Abdo <abdo@member.fsf.org>
License-Expression: GPL-3.0-or-later
License-File: LICENSE
Classifier: Development Status :: 4 - Beta
Classifier: License :: OSI Approved :: GNU General Public License v3 or later (GPLv3+)
Classifier: Programming Language :: Python
Classifier: Topic :: Scientific/Engineering :: Artificial Intelligence
Classifier: Topic :: Scientific/Engineering :: Visualization
Classifier: Topic :: Sociology
Requires-Python: >=3.8
Requires-Dist: bokeh
Requires-Dist: colorcet
Requires-Dist: lxml
Requires-Dist: matplotlib
Requires-Dist: numpy
Requires-Dist: pandas
Requires-Dist: scipy
Requires-Dist: spacy
Requires-Dist: tqdm
